README.md
setup.cfg
setup.py
simobility/__init__.py
simobility/__version__.py
simobility/utils.py
simobility.egg-info/PKG-INFO
simobility.egg-info/SOURCES.txt
simobility.egg-info/dependency_links.txt
simobility.egg-info/not-zip-safe
simobility.egg-info/requires.txt
simobility.egg-info/top_level.txt
simobility/core/__init__.py
simobility/core/booking.py
simobility/core/booking_service.py
simobility/core/clock.py
simobility/core/dispatcher.py
simobility/core/fleet.py
simobility/core/itinerary.py
simobility/core/jobs.py
simobility/core/loggers.py
simobility/core/metrics.py
simobility/core/position.py
simobility/core/state_machine.py
simobility/core/state_transitions.py
simobility/core/tools.py
simobility/core/vehicle.py
simobility/core/vehicle_engine.py
simobility/routers/__init__.py
simobility/routers/base_router.py
simobility/routers/caching_router.py
simobility/routers/linear_router.py
simobility/routers/osrm_router.py
simobility/routers/route.py
simobility/routers/utils.py
simobility/simulator/__init__.py
simobility/simulator/simulator.py