Metadata-Version: 2.1
Name: simobility
Version: 0.3.0
Summary: Lightweight mobility simulation for quick algorithm prototyping
Home-page: https://github.com/sash-ko/simobility
Author: Oleksandr Lysenko
Author-email: sashkolysenko@gmail.com
License: MIT
Download-URL: https://github.com/sash-ko/simobility/archive/v0.3.0.tar.gz
Platform: UNKNOWN
Requires-Python: >=3.7.*
Provides-Extra: dev
